LICENSE
README.md
pyproject.toml
python-Readme.md
setup.py
bindings/python/tree_sitter_usfm3/__init__.py
bindings/python/tree_sitter_usfm3/__init__.pyi
bindings/python/tree_sitter_usfm3/binding.c
bindings/python/tree_sitter_usfm3/py.typed
src/parser.c
src/tree_sitter/alloc.h
src/tree_sitter/array.h
src/tree_sitter/parser.h
tree_sitter_usfm3.egg-info/PKG-INFO
tree_sitter_usfm3.egg-info/SOURCES.txt
tree_sitter_usfm3.egg-info/dependency_links.txt
tree_sitter_usfm3.egg-info/not-zip-safe
tree_sitter_usfm3.egg-info/requires.txt
tree_sitter_usfm3.egg-info/top_level.txt