Metadata-Version: 2.4
Name: tree-sitter-usfm3
Version: 3.2.0b1
Summary: Usfm3 grammar for tree-sitter
Author-email: BCS Team <joel@bridgeconn.com>
Maintainer-email: Kavitha Raju <kavitha.raju@bridgeconn.com>, Joel Mathew <joel@bridgeconn.com>
License: MIT
Project-URL: Homepage, https://github.com/Bridgeconn/usfm-grammar/tree/version-3/tree-sitter-usfm3/python-Readme.md
Keywords: incremental,parsing,tree-sitter,usfm3
Classifier: Intended Audience :: Developers
Classifier: License :: OSI Approved :: MIT License
Classifier: Topic :: Software Development :: Compilers
Classifier: Topic :: Text Processing :: Linguistic
Classifier: Typing :: Typed
Requires-Python: >=3.8
License-File: LICENSE
Provides-Extra: core
Requires-Dist: tree-sitter~=0.21; extra == "core"
Dynamic: license-file
